[
	{ "s": "ЗА", "p": [11] },
	{ "s": "ЗАБЫТЬ", "p": [8] },
	{ "s": "ЗАЕЗДА", "p": [4] },
	{ "s": "ЗАКРЫВАЕТ", "p": [10, 8, 4] },
	{ "s": "ЗАКРЫВАЕТСЯ", "p": [7] },
	{ "s": "ЗАМЕНИТЕ", "p": [8] },
	{ "s": "ЗАНЕСЕННЫХ", "p": [9] },
	{ "s": "ЗАНОСИТ", "p": [4] },
	{ "s": "ЗАСЕЛЕНИЕ", "p": [4, 11, 2] },
	{ "s": "ЗАСЕЛЕНИЯ", "p": [4, 11, 3] },
	{ "s": "ЗАСЕЛЕННЫХ", "p": [3] },
	{ "s": "ЗАСЕЛИТЬ", "p": [4, 3] },
	{ "s": "ЗАСЕЛЯТЬ", "p": [4] },
	{ "s": "ЗАТЕМ", "p": [9] },
	{ "s": "ЗАЯВЛЕНИЕ", "p": [8, 6] },
	{ "s": "ЗАЯВЛЕНИИ", "p": [8] },
	{ "s": "ЗП", "p": [9, 6, 3, 2] }
]